cpip/CPIPMain.py
cpip/CppCondGraphToHtml.py
cpip/DupeRelink.py
cpip/FileStatus.py
cpip/IncGraphSVG.py
cpip/IncGraphSVGBase.py
cpip/IncGraphXML.py
cpip/IncList.py
cpip/ItuToHtml.py
cpip/MacroHistoryHtml.py
cpip/TokenCss.py
cpip/Tu2Html.py
cpip/TuIndexer.py
cpip/__init__.py
cpip/__version__.py
cpip/cpp.py
cpip/main.py
cpip/strip_comments.py
cpip/core/ConstantExpression.py
cpip/core/CppCond.py
cpip/core/CppDiagnostic.py
cpip/core/FileIncludeGraph.py
cpip/core/FileIncludeStack.py
cpip/core/FileLocation.py
cpip/core/IncludeHandler.py
cpip/core/ItuToTokens.py
cpip/core/MacroEnv.py
cpip/core/PpDefine.py
cpip/core/PpLexer.py
cpip/core/PpToken.py
cpip/core/PpTokenCount.py
cpip/core/PpTokeniser.py
cpip/core/PpWhitespace.py
cpip/core/PragmaHandler.py
cpip/core/__init__.py
cpip/plot/Coord.py
cpip/plot/PlotNode.py
cpip/plot/SVGWriter.py
cpip/plot/TreePlotTransform.py
cpip/plot/__init__.py
cpip/util/BufGen.py
cpip/util/CommonPrefix.py
cpip/util/Cpp.py
cpip/util/DictTree.py
cpip/util/DirWalk.py
cpip/util/HtmlUtils.py
cpip/util/ListGen.py
cpip/util/MatrixRep.py
cpip/util/MaxMunchGen.py
cpip/util/MultiPassString.py
cpip/util/OaS.py
cpip/util/StrTree.py
cpip/util/Tree.py
cpip/util/XmlWrite.py
cpip/util/__init__.py
cpip-0.9.9.dist-info/AUTHORS.rst
cpip-0.9.9.dist-info/LICENCE
cpip-0.9.9.dist-info/METADATA
cpip-0.9.9.dist-info/WHEEL
cpip-0.9.9.dist-info/entry_points.txt
cpip-0.9.9.dist-info/top_level.txt
cpip-0.9.9.dist-info/RECORD
