Metadata-Version: 2.1
Name: cpip
Version: 0.9.9
Summary: CPIP is a C/C++ Preprocessor implemented in Python.
Home-page: https://github.com/paulross/cpip
Author: Paul Ross
Author-email: apaulross@gmail.com
License: GPL-2.0-or-later
Keywords: cpip
Classifier: Development Status :: 4 - Beta
Classifier: Environment :: Console
Classifier: Intended Audience :: Developers
Classifier: License :: OSI Approved :: GNU General Public License v2 (GPLv2)
Classifier: Natural Language :: English
Classifier: Programming Language :: Python :: 3
Classifier: Programming Language :: Python :: 3.6
Classifier: Programming Language :: Python :: 3.7
Classifier: Programming Language :: Python :: 3.8
Classifier: Programming Language :: Python :: 3.9
Classifier: Programming Language :: Python :: 3.10
Classifier: Programming Language :: Python :: 3.11
Classifier: Operating System :: OS Independent
License-File: LICENCE
License-File: AUTHORS.rst
